RsWaveform/__init__.py
RsWaveform/__main__.py
RsWaveform/load_interface.py
RsWaveform/parent_storage.py
RsWaveform/py.typed
RsWaveform/save_interface.py
RsWaveform/storage.py
RsWaveform/iqtar/__init__.py
RsWaveform/iqtar/load.py
RsWaveform/iqtar/save.py
RsWaveform/iqw/__init__.py
RsWaveform/iqw/load.py
RsWaveform/iqw/save.py
RsWaveform/meta/__init__.py
RsWaveform/meta/defaults.py
RsWaveform/meta/meta_base.py
RsWaveform/meta/meta_iqtar.py
RsWaveform/meta/meta_wv.py
RsWaveform/npz/README.md
RsWaveform/npz/__init__.py
RsWaveform/npz/load.py
RsWaveform/npz/npz_inteface.py
RsWaveform/npz/save.py
RsWaveform/utility/__init__.py
RsWaveform/utility/dsp.py
RsWaveform/utility/fake_jit.py
RsWaveform/utility/file_handling.py
RsWaveform/utility/integer_indexedproperty.py
RsWaveform/utility/meta_utils.py
RsWaveform/wv/__init__.py
RsWaveform/wv/load.py
RsWaveform/wv/save.py
RsWaveform/wv/utility/__init__.py
RsWaveform/wv/utility/array_to_bytes.py
rswaveform-0.5.0.dist-info/licenses/LICENSE
rswaveform-0.5.0.dist-info/METADATA
rswaveform-0.5.0.dist-info/WHEEL
rswaveform-0.5.0.dist-info/top_level.txt
rswaveform-0.5.0.dist-info/RECORD
