Metadata-Version: 2.4
Name: RsWaveform
Version: 0.5.0
Summary: Load, manipulate and save R&S waveform files
Author-email: "Rohde & Schwarz GmbH & Co. KG" <info@rohde-schwarz.com>
Maintainer-email: Carsten Sauerbrey <Carsten.Sauerbrey@rohde-schwarz.com>, Daniela Rossetto <Daniela.Rossetto@rohde-schwarz.com>
License: MIT
Project-URL: project, https://github.com/Rohde-Schwarz/RsWaveform
Keywords: waveform,signal,load,save
Platform: Unix
Platform: Linux
Platform: Windows
Classifier: Development Status :: 4 - Beta
Classifier: License :: OSI Approved :: MIT License
Classifier: Operating System :: OS Independent
Classifier: Programming Language :: Python :: 3.9
Classifier: Programming Language :: Python :: 3.10
Classifier: Programming Language :: Python :: 3.11
Classifier: Programming Language :: Python :: 3.12
Requires-Python: >=3.9
License-File: LICENSE
Requires-Dist: numpy
Requires-Dist: indexedproperty
Provides-Extra: docs
Requires-Dist: sphinx; extra == "docs"
Requires-Dist: sphinx-rtd-theme; extra == "docs"
Requires-Dist: myst-parser; extra == "docs"
Provides-Extra: test
Requires-Dist: pytest; extra == "test"
Requires-Dist: coverage[toml]; extra == "test"
Requires-Dist: pytest-cov; extra == "test"
Requires-Dist: pytest-mock; extra == "test"
Provides-Extra: jit
Requires-Dist: numba; extra == "jit"
Provides-Extra: msgpack
Requires-Dist: msgpack; extra == "msgpack"
Requires-Dist: msgpack-numpy; extra == "msgpack"
Dynamic: license-file
